{
  "adapter_id": "adapter:wave64-pcm-to-au-pcm-static",
  "version": "0.1.0",
  "capsule": {
    "id": "capsule:wave64-pcm-to-au-pcm",
    "version_requirement": "^0.1.0"
  },
  "protocol": {
    "name": "everythingx-adapter-protocol",
    "version_requirement": "0.1"
  },
  "transport": {
    "kind": "static-rust",
    "entrypoint": "GeneratedPcmAdapter"
  },
  "capabilities": [
    {
      "capability_id": "capability:wave64-pcm-to-au-pcm/pcm-exact/native-portable",
      "capsule_entrypoint": "convert",
      "strategy": "pcm-exact",
      "backend": "native-portable",
      "inputs": [
        "exfmt:audio:wave64-pcm"
      ],
      "outputs": [
        "exfmt:audio:au-pcm"
      ],
      "preconditions": [
        "Input is supported integer PCM in Sony Wave64 PCM"
      ],
      "effects": [
        "Output is Sun AU/SND PCM"
      ],
      "invariants": [
        "Sample rate",
        "Frame count",
        "Channel count",
        "PCM sample sequence"
      ],
      "computability": "semantic_lossless",
      "loss": {
        "payload": "none",
        "temporal": "none",
        "structure": "normalized",
        "metadata": "unbounded"
      },
      "default_options": {
        "strict_header_consistency": true,
        "buffer_size": 65536,
        "max_channels": 256
      },
      "defaults_are_runnable": true,
      "execution": {
        "streaming": false,
        "seek_required": false,
        "cost_evidence": [
          "registry/performance/baseline.json#capability:wave64-pcm-to-au-pcm/pcm-exact/native-portable"
        ]
      },
      "report_mapping": {
        "unknown_fields_are_preserved": true,
        "rules": [
          "PCM facts map to capsule_report",
          "static Adapter buffers forward-only protocol input"
        ]
      }
    }
  ]
}
